tinydocs/__init__.py
tinydocs/classes.py
tinydocs/main.py
tinydocs/parser.py
tinydocs/transformer.py
tinydocs-0.0.2.dist-info/METADATA
tinydocs-0.0.2.dist-info/WHEEL
tinydocs-0.0.2.dist-info/entry_points.txt
tinydocs-0.0.2.dist-info/top_level.txt
tinydocs-0.0.2.dist-info/RECORD
