Metadata-Version: 2.1
Name: tinydocs
Version: 0.0.2
Summary: Lightweight autodoc for github readme
Author-email: António Leitão <aleitao@novaims.unl.pt>
Project-URL: Homepage, https://github.com/antonio-leitao/docme
Classifier: Programming Language :: Python :: 3
Classifier: License :: OSI Approved :: MIT License
Classifier: Operating System :: OS Independent
Requires-Python: >=3.9
Requires-Dist: numpydoc (>=1.5.0)
